{
  "articleKrysto": [
    {
      "id": 1001,
      "type": "objet",
      "nom": "mousquetons",
      "cover": "mousquetons.jpeg",
      "description": "Ce magnifique mousquetons en plastique recycle vous accompagneras partout",
      "altText": "un mousquetons en plastique recycler krysto ",
      "typeDePlastique": ["hdpe", "pp"],
      "poidGr": 10,
      "prix": 200,
      "couleur": ["bleu", "jaune", "rouge", "blanc", "noir"],
      "nbDeVentes": 0,
      "stock": 1000
    },
    {
      "id": 1002,
      "type": "objet",
      "nom": "mousquetons",
      "cover": "mousquetons.jpeg",
      "description": "Ce magnifique mousquetons en plastique recycle vous accompagneras partout",
      "altText": "un mousquetons en plastique recycler krysto ",
      "typeDePlastique": ["hdpe", "pp"],
      "poidGr": 10,
      "prix": 200,
      "couleur": ["bleu", "jaune", "rouge", "blanc", "noir"],
      "nbDeVentes": 0,
      "stock": 1000
    },
    {
      "id": 1002,
      "type": "construction",
      "nom": "Brique",
      "cover": "brique.jpeg",
      "description": "Laissez libre court a votre imagination avec les briques krysto",
      "altText": "Un lot de brique krysto ",
      "typeDePlastique": ["hdpe", "pp"],
      "poidGr": 1500,
      "prix": 455,
      "couleur": ["bleu", "jaune", "rouge", "blanc", "noir"],
      "nbDeVentes": 0,
      "stock": 1000
    },
    {
      "id": 1002,
      "type": "mobilier",
      "nom": "Banc Krysto",
      "cover": "banc.jpeg",
      "description": "contempler votre jardin confortablement installer sur un banc ecologique",
      "altText": "Une femme assise sur un banc Krysto",
      "typeDePlastique": ["hdpe", "pp"],
      "poidGr": 5000,
      "prix": 8000,
      "couleur": ["bleu", "jaune", "rouge", "blanc", "noir"],
      "nbDeVentes": 0,
      "stock": 15
    },
    {
      "id": 1003,
      "type": "planche 200",
      "nom": "planche 200",
      "cover": "planche200.jpeg",
      "description": "imaginez , construisez",
      "altText": "Un lot de planches Krysto",
      "typeDePlastique": ["hdpe", "pp", "ps"],
      "poidGr": 3000,
      "prix": 2000,
      "couleur": ["bleu", "jaune", "rouge", "blanc", "noir"],
      "nbDeVentes": 0,
      "stock": 100
    },
    {
      "id": 1004,
      "type": "planche 150",
      "nom": "planche 150",
      "cover": "planche150.jpeg",
      "description": "imaginez , construisez",
      "altText": "Un lot de planches Krysto",
      "typeDePlastique": ["hdpe", "pp", "ps"],
      "poidGr": 2025,
      "prix": 1520,
      "couleur": ["bleu", "jaune", "rouge", "blanc", "noir"],
      "nbDeVentes": 0,
      "stock": 100
    },
    {
      "id": 1005,
      "type": "planche 070",
      "nom": "planche 070",
      "cover": "planche070.jpeg",
      "description": "imaginez , construisez",
      "altText": "Un lot de planches Krysto",
      "typeDePlastique": ["hdpe", "pp", "ps"],
      "poidGr": 1005,
      "prix": 1050,
      "couleur": ["bleu", "jaune", "rouge", "blanc", "noir"],
      "nbDeVentes": 0,
      "stock": 150
    },
    {
      "id": 1006,
      "type": "objet",
      "nom": "peignesPM",
      "cover": "peignePM.jpeg",
      "description": "peignes de plages en plastique recycle",
      "altText": "un peignes Krysto sur une plage deserte ",
      "typeDePlastique": ["hdpe", "pp"],
      "poidGr": 10,
      "prix": 700,
      "couleur": ["bleu", "jaune", "rouge", "blanc", "noir"],
      "nbDeVentes": 0,
      "stock": 500
    },
    {
      "id": 1006,
      "type": "objet",
      "nom": "peignesGM",
      "cover": "peigneGM.jpeg",
      "description": "peignes de plages en plastique recycle",
      "altText": "un peignes Krysto sur une plage deserte ",
      "typeDePlastique": ["hdpe", "pp"],
      "poidGr": 15,
      "prix": 900,
      "couleur": ["bleu", "jaune", "rouge", "blanc", "noir"],
      "nbDeVentes": 0,
      "stock": 500
    },
    {
      "id": 1007,
      "type": "objet",
      "nom": "support tablette et telephone",
      "cover": "supportTablette.jpeg",
      "description": "un support de telephone et tablette",
      "altText": "un support de telephone Krysto supportant une tablette",
      "typeDePlastique": ["hdpe", "pp"],
      "poidGr": 15,
      "prix": 200,
      "couleur": ["bleu", "jaune", "rouge", "blanc", "noir"],
      "nbDeVentes": 0,
      "stock": 400
    }
  ]
}
